[{"national_number":"415","evolution":null,"sprites":{"normal":"https://img.pokemondb.net/sprites/omega-ruby-alpha-sapphire/dex/normal/combee.png","large":"https://img.pokemondb.net/artwork/combee.jpg","animated":"https://img.pokemondb.net/sprites/black-white/anim/normal/combee.gif"},"name":"Combee","type":["Bug","Flying"],"total":244,"hp":30,"attack":30,"defense":42,"sp_atk":30,"sp_def":42,"speed":70},{"national_number":"416","evolution":null,"sprites":{"normal":"https://img.pokemondb.net/sprites/omega-ruby-alpha-sapphire/dex/normal/vespiquen.png","large":"https://img.pokemondb.net/artwork/vespiquen.jpg","animated":"https://img.pokemondb.net/sprites/black-white/anim/normal/vespiquen.gif"},"name":"Vespiquen","type":["Bug","Flying"],"total":474,"hp":70,"attack":80,"defense":102,"sp_atk":80,"sp_def":102,"speed":40},{"national_number":"417","evolution":null,"sprites":{"normal":"https://img.pokemondb.net/sprites/omega-ruby-alpha-sapphire/dex/normal/pachirisu.png","large":"https://img.pokemondb.net/artwork/pachirisu.jpg","animated":"https://img.pokemondb.net/sprites/black-white/anim/normal/pachirisu.gif"},"name":"Pachirisu","type":["Electric"],"total":405,"hp":60,"attack":45,"defense":70,"sp_atk":45,"sp_def":90,"speed":95},{"national_number":"418","evolution":null,"sprites":{"normal":"https://img.pokemondb.net/sprites/omega-ruby-alpha-sapphire/dex/normal/buizel.png","large":"https://img.pokemondb.net/artwork/buizel.jpg","animated":"https://img.pokemondb.net/sprites/black-white/anim/normal/buizel.gif"},"name":"Buizel","type":["Water"],"total":330,"hp":55,"attack":65,"defense":35,"sp_atk":60,"sp_def":30,"speed":85},{"national_number":"419","evolution":null,"sprites":{"normal":"https://img.pokemondb.net/sprites/omega-ruby-alpha-sapphire/dex/normal/floatzel.png","large":"https://img.pokemondb.net/artwork/floatzel.jpg","animated":"https://img.pokemondb.net/sprites/black-white/anim/normal/floatzel.gif"},"name":"Floatzel","type":["Water"],"total":495,"hp":85,"attack":105,"defense":55,"sp_atk":85,"sp_def":50,"speed":115},{"national_number":"420","evolution":null,"sprites":{"normal":"https://img.pokemondb.net/sprites/omega-ruby-alpha-sapphire/dex/normal/cherubi.png","large":"https://img.pokemondb.net/artwork/cherubi.jpg","animated":"https://img.pokemondb.net/sprites/black-white/anim/normal/cherubi.gif"},"name":"Cherubi","type":["Grass"],"total":275,"hp":45,"attack":35,"defense":45,"sp_atk":62,"sp_def":53,"speed":35},{"national_number":"421","evolution":null,"sprites":{"normal":"https://img.pokemondb.net/sprites/omega-ruby-alpha-sapphire/dex/normal/cherrim.png","large":"https://img.pokemondb.net/artwork/cherrim.jpg","animated":"https://img.pokemondb.net/sprites/black-white/anim/normal/cherrim.gif"},"name":"Cherrim","type":["Grass"],"total":450,"hp":70,"attack":60,"defense":70,"sp_atk":87,"sp_def":78,"speed":85},{"national_number":"422","evolution":null,"sprites":{"normal":"https://img.pokemondb.net/sprites/omega-ruby-alpha-sapphire/dex/normal/shellos.png","large":"https://img.pokemondb.net/artwork/shellos.jpg","animated":"https://img.pokemondb.net/sprites/black-white/anim/normal/shellos.gif"},"name":"Shellos","type":["Water"],"total":325,"hp":76,"attack":48,"defense":48,"sp_atk":57,"sp_def":62,"speed":34},{"national_number":"423","evolution":null,"sprites":{"normal":"https://img.pokemondb.net/sprites/omega-ruby-alpha-sapphire/dex/normal/gastrodon.png","large":"https://img.pokemondb.net/artwork/gastrodon.jpg","animated":"https://img.pokemondb.net/sprites/black-white/anim/normal/gastrodon.gif"},"name":"Gastrodon","type":["Water","Ground"],"total":475,"hp":111,"attack":83,"defense":68,"sp_atk":92,"sp_def":82,"speed":39},{"national_number":"424","evolution":null,"sprites":{"normal":"https://img.pokemondb.net/sprites/omega-ruby-alpha-sapphire/dex/normal/ambipom.png","large":"https://img.pokemondb.net/artwork/ambipom.jpg","animated":"https://img.pokemondb.net/sprites/black-white/anim/normal/ambipom.gif"},"name":"Ambipom","type":["Normal"],"total":482,"hp":75,"attack":100,"defense":66,"sp_atk":60,"sp_def":66,"speed":115},{"national_number":"425","evolution":null,"sprites":{"normal":"https://img.pokemondb.net/sprites/omega-ruby-alpha-sapphire/dex/normal/drifloon.png","large":"https://img.pokemondb.net/artwork/drifloon.jpg","animated":"https://img.pokemondb.net/sprites/black-white/anim/normal/drifloon.gif"},"name":"Drifloon","type":["Ghost","Flying"],"total":348,"hp":90,"attack":50,"defense":34,"sp_atk":60,"sp_def":44,"speed":70},{"national_number":"426","evolution":null,"sprites":{"normal":"https://img.pokemondb.net/sprites/omega-ruby-alpha-sapphire/dex/normal/drifblim.png","large":"https://img.pokemondb.net/artwork/drifblim.jpg","animated":"https://img.pokemondb.net/sprites/black-white/anim/normal/drifblim.gif"},"name":"Drifblim","type":["Ghost","Flying"],"total":498,"hp":150,"attack":80,"defense":44,"sp_atk":90,"sp_def":54,"speed":80},{"national_number":"427","evolution":null,"sprites":{"normal":"https://img.pokemondb.net/sprites/omega-ruby-alpha-sapphire/dex/normal/buneary.png","large":"https://img.pokemondb.net/artwork/buneary.jpg","animated":"https://img.pokemondb.net/sprites/black-white/anim/normal/buneary.gif"},"name":"Buneary","type":["Normal"],"total":350,"hp":55,"attack":66,"defense":44,"sp_atk":44,"sp_def":56,"speed":85},{"national_number":"428","evolution":{"name":"Mega Lopunny"},"sprites":{"normal":"https://img.pokemondb.net/sprites/omega-ruby-alpha-sapphire/dex/normal/lopunny.png","large":"https://img.pokemondb.net/artwork/lopunny.jpg","animated":"https://img.pokemondb.net/sprites/black-white/anim/normal/lopunny.gif"},"name":"Lopunny","type":["Normal","Fighting"],"total":580,"hp":65,"attack":136,"defense":94,"sp_atk":54,"sp_def":96,"speed":135},{"national_number":"428","evolution":null,"sprites":{"normal":"https://img.pokemondb.net/sprites/omega-ruby-alpha-sapphire/dex/normal/lopunny.png","large":"https://img.pokemondb.net/artwork/lopunny.jpg","animated":"https://img.pokemondb.net/sprites/black-white/anim/normal/lopunny.gif"},"name":"Lopunny","type":["Normal"],"total":480,"hp":65,"attack":76,"defense":84,"sp_atk":54,"sp_def":96,"speed":105},{"national_number":"429","evolution":null,"sprites":{"normal":"https://img.pokemondb.net/sprites/omega-ruby-alpha-sapphire/dex/normal/mismagius.png","large":"https://img.pokemondb.net/artwork/mismagius.jpg","animated":"https://img.pokemondb.net/sprites/black-white/anim/normal/mismagius.gif"},"name":"Mismagius","type":["Ghost"],"total":495,"hp":60,"attack":60,"defense":60,"sp_atk":105,"sp_def":105,"speed":105},{"national_number":"430","evolution":null,"sprites":{"normal":"https://img.pokemondb.net/sprites/omega-ruby-alpha-sapphire/dex/normal/honchkrow.png","large":"https://img.pokemondb.net/artwork/honchkrow.jpg","animated":"https://img.pokemondb.net/sprites/black-white/anim/normal/honchkrow.gif"},"name":"Honchkrow","type":["Dark","Flying"],"total":505,"hp":100,"attack":125,"defense":52,"sp_atk":105,"sp_def":52,"speed":71},{"national_number":"431","evolution":null,"sprites":{"normal":"https://img.pokemondb.net/sprites/omega-ruby-alpha-sapphire/dex/normal/glameow.png","large":"https://img.pokemondb.net/artwork/glameow.jpg","animated":"https://img.pokemondb.net/sprites/black-white/anim/normal/glameow.gif"},"name":"Glameow","type":["Normal"],"total":310,"hp":49,"attack":55,"defense":42,"sp_atk":42,"sp_def":37,"speed":85},{"national_number":"432","evolution":null,"sprites":{"normal":"https://img.pokemondb.net/sprites/omega-ruby-alpha-sapphire/dex/normal/purugly.png","large":"https://img.pokemondb.net/artwork/purugly.jpg","animated":"https://img.pokemondb.net/sprites/black-white/anim/normal/purugly.gif"},"name":"Purugly","type":["Normal"],"total":452,"hp":71,"attack":82,"defense":64,"sp_atk":64,"sp_def":59,"speed":112},{"national_number":"433","evolution":null,"sprites":{"normal":"https://img.pokemondb.net/sprites/omega-ruby-alpha-sapphire/dex/normal/chingling.png","large":"https://img.pokemondb.net/artwork/chingling.jpg","animated":"https://img.pokemondb.net/sprites/black-white/anim/normal/chingling.gif"},"name":"Chingling","type":["Psychic"],"total":285,"hp":45,"attack":30,"defense":50,"sp_atk":65,"sp_def":50,"speed":45}]